intake_spark/__init__.py
intake_spark/_version.py
intake_spark/base.py
intake_spark/spark_cat.py
intake_spark/spark_sources.py
tests/__init__.py
tests/sample1.csv
tests/test_discovery.py
tests/test_spark.py
tests/util.py
intake_spark-0.1.2.dist-info/LICENSE
intake_spark-0.1.2.dist-info/METADATA
intake_spark-0.1.2.dist-info/WHEEL
intake_spark-0.1.2.dist-info/entry_points.txt
intake_spark-0.1.2.dist-info/pbr.json
intake_spark-0.1.2.dist-info/top_level.txt
intake_spark-0.1.2.dist-info/RECORD
