Metadata-Version: 2.1
Name: intake-spark
Version: 0.1.2
Summary: Apache Spark plugin for Intake
Home-page: https://github.com/ContinuumIO/intake-spark
Maintainer: Martin Durant
Maintainer-email: mdurant@anaconda.com
License: BSD
Platform: UNKNOWN
Requires-Dist: intake
Requires-Dist: pyspark
Requires-Dist: dask
